{
    "Video1": {
        "74": [
            [
                "right_ankle_x_vel",
                -1.777191162109375
            ],
            [
                "right_ankle_y_vel",
                -16.30535888671875
            ],
            [
                "left_ankle_x_vel",
                2.8582000732421875
            ],
            [
                "left_ankle_y_vel",
                9.640289306640625
            ],
            [
                "shin_velocity_left",
                -1.7123870849609375
            ],
            [
                "shin_velocity_right",
                -7.152069091796875
            ],
            [
                "left_tibial",
                2.99573016166687
            ],
            [
                "right_tibial",
                4.492762088775635
            ],
            "L"
        ],
        "115": [
            [
                "right_ankle_x_vel",
                8.636016845703125
            ],
            [
                "right_ankle_y_vel",
                8.58154296875
            ],
            [
                "left_ankle_x_vel",
                -10.003692626953125
            ],
            [
                "left_ankle_y_vel",
                -7.19317626953125
            ],
            [
                "shin_velocity_left",
                -2.89080810546875
            ],
            [
                "shin_velocity_right",
                -8.69696044921875
            ],
            [
                "left_tibial",
                4.290290832519531
            ],
            [
                "right_tibial",
                3.114612579345703
            ],
            "R"
        ],
        "127": [
            [
                "right_ankle_x_vel",
                -19.900848388671875
            ],
            [
                "right_ankle_y_vel",
                -5.49603271484375
            ],
            [
                "left_ankle_x_vel",
                12.795578002929688
            ],
            [
                "left_ankle_y_vel",
                5.11456298828125
            ],
            [
                "shin_velocity_left",
                -13.100296020507812
            ],
            [
                "shin_velocity_right",
                8.321441650390625
            ],
            [
                "left_tibial",
                3.075767993927002
            ],
            [
                "right_tibial",
                4.547821998596191
            ],
            "L"
        ],
        "139": [
            [
                "right_ankle_x_vel",
                -109.30538940429688
            ],
            [
                "right_ankle_y_vel",
                50.99383544921875
            ],
            [
                "left_ankle_x_vel",
                118.01567077636719
            ],
            [
                "left_ankle_y_vel",
                -56.166015625
            ],
            [
                "shin_velocity_left",
                -82.06500244140625
            ],
            [
                "shin_velocity_right",
                61.091217041015625
            ],
            [
                "left_tibial",
                4.517012119293213
            ],
            [
                "right_tibial",
                3.1882829666137695
            ],
            "R"
        ],
        "150": [
            [
                "right_ankle_x_vel",
                -17.417449951171875
            ],
            [
                "right_ankle_y_vel",
                -8.2589111328125
            ],
            [
                "left_ankle_x_vel",
                15.097824096679688
            ],
            [
                "left_ankle_y_vel",
                16.2176513671875
            ],
            [
                "shin_velocity_left",
                -16.896377563476562
            ],
            [
                "shin_velocity_right",
                1.7824249267578125
            ],
            [
                "left_tibial",
                2.9467480182647705
            ],
            [
                "right_tibial",
                4.534536838531494
            ],
            "L"
        ],
        "162": [
            [
                "right_ankle_x_vel",
                -16.621322631835938
            ],
            [
                "right_ankle_y_vel",
                33.0281982421875
            ],
            [
                "left_ankle_x_vel",
                13.210525512695312
            ],
            [
                "left_ankle_y_vel",
                -26.674560546875
            ],
            [
                "shin_velocity_left",
                -16.991058349609375
            ],
            [
                "shin_velocity_right",
                -2.3725738525390625
            ],
            [
                "left_tibial",
                3.0237438678741455
            ],
            [
                "right_tibial",
                4.295137405395508
            ],
            "R"
        ],
        "174": [
            [
                "right_ankle_x_vel",
                -72.64692687988281
            ],
            [
                "right_ankle_y_vel",
                16.609375
            ],
            [
                "left_ankle_x_vel",
                26.5045166015625
            ],
            [
                "left_ankle_y_vel",
                16.68896484375
            ],
            [
                "shin_velocity_left",
                -28.917526245117188
            ],
            [
                "shin_velocity_right",
                35.95500183105469
            ],
            [
                "left_tibial",
                2.9871091842651367
            ],
            [
                "right_tibial",
                4.6262125968933105
            ],
            "L"
        ],
        "202": [
            [
                "right_ankle_x_vel",
                -19.317657470703125
            ],
            [
                "right_ankle_y_vel",
                -0.3944091796875
            ],
            [
                "left_ankle_x_vel",
                36.052734375
            ],
            [
                "left_ankle_y_vel",
                13.25897216796875
            ],
            [
                "shin_velocity_left",
                -37.66932678222656
            ],
            [
                "shin_velocity_right",
                3.18072509765625
            ],
            [
                "left_tibial",
                3.0377891063690186
            ],
            [
                "right_tibial",
                4.525039196014404
            ],
            "L"
        ],
        "224": [
            [
                "right_ankle_x_vel",
                -18.3828125
            ],
            [
                "right_ankle_y_vel",
                -4.39569091796875
            ],
            [
                "left_ankle_x_vel",
                26.068130493164062
            ],
            [
                "left_ankle_y_vel",
                13.98974609375
            ],
            [
                "shin_velocity_left",
                -25.262741088867188
            ],
            [
                "shin_velocity_right",
                5.7102813720703125
            ],
            [
                "left_tibial",
                2.950428009033203
            ],
            [
                "right_tibial",
                4.593654155731201
            ],
            "L"
        ],
        "236": [
            [
                "right_ankle_x_vel",
                -90.69290161132812
            ],
            [
                "right_ankle_y_vel",
                53.472442626953125
            ],
            [
                "left_ankle_x_vel",
                81.35289001464844
            ],
            [
                "left_ankle_y_vel",
                -38.60906982421875
            ],
            [
                "shin_velocity_left",
                -58.92344665527344
            ],
            [
                "shin_velocity_right",
                40.40440368652344
            ],
            [
                "left_tibial",
                4.613903999328613
            ],
            [
                "right_tibial",
                3.1058874130249023
            ],
            "R"
        ],
        "250": [
            [
                "right_ankle_x_vel",
                -20.514739990234375
            ],
            [
                "right_ankle_y_vel",
                -2.298858642578125
            ],
            [
                "left_ankle_x_vel",
                12.521881103515625
            ],
            [
                "left_ankle_y_vel",
                8.64764404296875
            ],
            [
                "shin_velocity_left",
                -7.2773590087890625
            ],
            [
                "shin_velocity_right",
                17.012237548828125
            ],
            [
                "left_tibial",
                2.9604849815368652
            ],
            [
                "right_tibial",
                4.5974531173706055
            ],
            "L"
        ],
        "261": [
            [
                "right_ankle_x_vel",
                -116.66520690917969
            ],
            [
                "right_ankle_y_vel",
                66.67965698242188
            ],
            [
                "left_ankle_x_vel",
                105.96697998046875
            ],
            [
                "left_ankle_y_vel",
                -44.27130126953125
            ],
            [
                "shin_velocity_left",
                -71.49822998046875
            ],
            [
                "shin_velocity_right",
                57.25709533691406
            ],
            [
                "left_tibial",
                3.0028915405273438
            ],
            [
                "right_tibial",
                4.4710774421691895
            ],
            "R"
        ],
        "272": [
            [
                "right_ankle_x_vel",
                -33.472503662109375
            ],
            [
                "right_ankle_y_vel",
                2.335693359375
            ],
            [
                "left_ankle_x_vel",
                30.090576171875
            ],
            [
                "left_ankle_y_vel",
                13.55316162109375
            ],
            [
                "shin_velocity_left",
                -22.172744750976562
            ],
            [
                "shin_velocity_right",
                15.907211303710938
            ],
            [
                "left_tibial",
                2.935762882232666
            ],
            [
                "right_tibial",
                4.583859920501709
            ],
            "L"
        ],
        "294": [
            [
                "right_ankle_x_vel",
                -27.95635986328125
            ],
            [
                "right_ankle_y_vel",
                -2.787353515625
            ],
            [
                "left_ankle_x_vel",
                23.838775634765625
            ],
            [
                "left_ankle_y_vel",
                15.996734619140625
            ],
            [
                "shin_velocity_left",
                -14.104583740234375
            ],
            [
                "shin_velocity_right",
                15.571868896484375
            ],
            [
                "left_tibial",
                2.8827438354492188
            ],
            [
                "right_tibial",
                4.542000770568848
            ],
            "L"
        ]
    }
}